ditto/__init__.py
ditto/_unittest.py
ditto/_version.py
ditto/exceptions.py
ditto/marks.py
ditto/plugin.py
ditto/snapshot.py
ditto/io/__init__.py
ditto/io/_json.py
ditto/io/_pickle.py
ditto/io/_plugins.py
ditto/io/_protocol.py
ditto/io/_yaml.py
pytest_ditto-0.1.2.dist-info/METADATA
pytest_ditto-0.1.2.dist-info/WHEEL
pytest_ditto-0.1.2.dist-info/entry_points.txt
pytest_ditto-0.1.2.dist-info/licenses/LICENSE
pytest_ditto-0.1.2.dist-info/RECORD
